wister/__init__.py
wister/control.py
wister/modes.py
wister/salt.dic
wister/utils.py
wister/version.py
wister/wister.py
wister-1.0.3.dist-info/LICENSE
wister-1.0.3.dist-info/METADATA
wister-1.0.3.dist-info/WHEEL
wister-1.0.3.dist-info/entry_points.txt
wister-1.0.3.dist-info/top_level.txt
wister-1.0.3.dist-info/RECORD
