Metadata-Version: 2.1
Name: wister
Version: 1.0.3
Summary: A wordlist generator tool, that allows you to supply a set of words, giving you the possibility to craft multiple variations from the given words, creating a unique and ideal wordlist to use regarding a specific target.
Home-page: https://github.com/cycurity/wister
Author: Cycurity
Author-email: cycurity@tutanota.com
License: UNKNOWN
Keywords: wister,wordlist,hacking,cybersecurity,bruteforcing
Platform: UNKNOWN
Classifier: Programming Language :: Python :: 3 :: Only
Classifier: Operating System :: OS Independent
Classifier: Environment :: Console
Classifier: Natural Language :: English
Classifier: Intended Audience :: Information Technology
Classifier: Intended Audience :: Developers
Classifier: License :: OSI Approved :: GNU General Public License v3 (GPLv3)
Classifier: Topic :: Security
Classifier: Topic :: Utilities
License-File: LICENSE
